MANIFEST.in
README.rst
setup.py
cciaa/__init__.py
cciaa.portlet.calendar.egg-info/PKG-INFO
cciaa.portlet.calendar.egg-info/SOURCES.txt
cciaa.portlet.calendar.egg-info/dependency_links.txt
cciaa.portlet.calendar.egg-info/entry_points.txt
cciaa.portlet.calendar.egg-info/namespace_packages.txt
cciaa.portlet.calendar.egg-info/not-zip-safe
cciaa.portlet.calendar.egg-info/requires.txt
cciaa.portlet.calendar.egg-info/top_level.txt
cciaa/portlet/__init__.py
cciaa/portlet/calendar/__init__.py
cciaa/portlet/calendar/configure.zcml
cciaa/portlet/calendar/portletcalendariocamerale.pt
cciaa/portlet/calendar/portletcalendariocamerale.py
cciaa/portlet/calendar/runI18ndude.sh
cciaa/portlet/calendar/browser/__init__.py
cciaa/portlet/calendar/browser/configure.zcml
cciaa/portlet/calendar/browser/searchevents.pt
cciaa/portlet/calendar/browser/searchevents.py
cciaa/portlet/calendar/browser/searchmonth.pt
cciaa/portlet/calendar/browser/searchmonth.py
cciaa/portlet/calendar/browser/styles/calendar.css
cciaa/portlet/calendar/i18n/plone-it.po
cciaa/portlet/calendar/i18n/plone.pot
cciaa/portlet/calendar/locales/cciaa.portlet.calendar-manual.pot
cciaa/portlet/calendar/locales/cciaa.portlet.calendar.pot
cciaa/portlet/calendar/locales/it/LC_MESSAGES/cciaa.portlet.calendar.mo
cciaa/portlet/calendar/locales/it/LC_MESSAGES/cciaa.portlet.calendar.po
cciaa/portlet/calendar/profiles/default/cssregistry.xml
cciaa/portlet/calendar/profiles/default/metadata.xml
cciaa/portlet/calendar/profiles/default/portlets.xml
cciaa/portlet/calendar/tests/__init__.py
cciaa/portlet/calendar/tests/base.py
cciaa/portlet/calendar/tests/test_portlet.py
docs/HISTORY.txt
docs/INSTALL.txt
docs/LICENSE.GPL
docs/LICENSE.txt