Metadata-Version: 1.1
Name: cciaa.portlet.calendar
Version: 1.3.0
Summary: Alternative calendar portlet for Plone that perform some additional search
Home-page: http://plone.org/products/cciaa.portlet.calendar
Author: RedTurtle Technology
Author-email: sviluppoplone@redturtle.it
License: GPL
Keywords: plone plonegov calendar portlet
Platform: UNKNOWN
Classifier: Framework :: Plone
Classifier: Framework :: Plone :: 3.3
Classifier: Framework :: Plone :: 4.0
Classifier: Framework :: Plone :: 4.1
Classifier: Framework :: Plone :: 4.2
Classifier: Framework :: Plone :: 4.3
Classifier: Programming Language :: Python
Classifier: Development Status :: 5 - Production/Stable
